{"primary cooking methods": ["boil", "cook", "bake"], "tools": ["oven", "oven", "saucepan", "baking dish"], "ingredients": [{"measurement": "cups", "name": "uncooked elbow macaroni", "quantity": "2"}, {"measurement": "tablespoons", "name": "butter", "quantity": "4"}, {"measurement": "tablespoons", "name": "all-purpose flour", "quantity": "2"}, {"measurement": "cups", "name": "milk", "quantity": "2"}, {"measurement": "pieces", "name": "onion, minced", "quantity": "1/4"}, {"measurement": "N/A", "name": "salt and pepper to taste", "quantity": "to taste"}, {"measurement": "pound", "name": "processed cheese food", "quantity": "1/4"}, {"measurement": "pound", "name": "shredded Cheddar cheese", "quantity": "1/4"}, {"measurement": "pound", "name": "shredded Swiss cheese", "quantity": "1/4"}], "servings": ["6 to 8 servings"], "directions": ["Preheat oven to 350 degrees F (175 degrees C).", "Prepare the elbow macaroni according to package directions.", "Meanwhile, melt the butter in a small saucepan over medium high heat", "Stir in the flour until a cream colored paste forms", "Then pour in the milk and stir constantly until this comes to a hard boil, then stir for 1 more minute", "Remove from heat and set aside.", "When the macaroni is cooked, spread 1/2 of it into the bottom of a lightly greased 9x13-inch baking dish", "Then layer 1/2 of the grated onion, 1/2 of the salt and pepper and 1/2 of each of the cheeses", "Repeat this one more time: macaroni, onion, salt and pepper and cheeses, and then pour the reserved white sauce over all", "Top off with small pats of butter to taste.", "Cover and bake at 350 degrees F (175 degrees C) for 45 minutes."], "all cooking methods": ["boil", "stir", "cream", "cook", "grate", "bake"]}